mcp_service.py
time_master/__init__.py
time_master/__main__.py
time_master/cli.py
time_master/config.py
time_master/core.py
time_master/exceptions.py
time_master/holiday_manager.py
time_master/mcp_service.py
time_master-0.1.2.dist-info/METADATA
time_master-0.1.2.dist-info/WHEEL
time_master-0.1.2.dist-info/entry_points.txt
time_master-0.1.2.dist-info/top_level.txt
time_master-0.1.2.dist-info/RECORD
