Metadata-Version: 2.4
Name: time-master
Version: 0.1.2
Summary: A canonical, high-reliability, developer-first modular common component for handling timezones and time in Python.
Author-email: "Kirky.X" <Kirky-X@outlook.com>
License: Apache 2.0
Project-URL: Repository, https://github.com/Kirky-X/mcps
Requires-Python: >=3.10
Requires-Dist: requests>=2.25.0
Requires-Dist: pytz>=2021.1
Requires-Dist: tzlocal>=4.1
Requires-Dist: thefuzz>=0.19.0
Requires-Dist: python-Levenshtein>=0.12.0
Requires-Dist: mcp>=1.13.1
Requires-Dist: holidays>=0.34
Requires-Dist: pycountry>=23.12.11
Provides-Extra: dev
Requires-Dist: ruff>=0.0.200; extra == "dev"
Requires-Dist: black>=21.0.0; extra == "dev"
